cpanel/REFERENCE
cpanel/USAGE
cpanel/__init__.py
cpanel/__main__.py
cpanel/cli.py
cpanel/core.py
cpanel/dispatcher.py
cpanel/util.py
cpanel/caller/__init__.py
cpanel/caller/accounts.py
cpanel/caller/addons.py
cpanel/caller/backup.py
cpanel/caller/bandwidth.py
cpanel/caller/cache.py
cpanel/caller/dir.py
cpanel/caller/dns.py
cpanel/caller/domains.py
cpanel/caller/features.py
cpanel/caller/files.py
cpanel/caller/ftp.py
cpanel/caller/ip.py
cpanel/caller/locale.py
cpanel/caller/logmanager.py
cpanel/caller/mail_accounts.py
cpanel/caller/mail_autoresponders.py
cpanel/caller/mail_boxes.py
cpanel/caller/mail_filters.py
cpanel/caller/mail_forwarders.py
cpanel/caller/mail_incoming.py
cpanel/caller/mail_login.py
cpanel/caller/mail_outgoing.py
cpanel/caller/mail_quota.py
cpanel/caller/mail_settings.py
cpanel/caller/mail_usage.py
cpanel/caller/mailman.py
cpanel/caller/mysql.py
cpanel/caller/postgres.py
cpanel/caller/quota.py
cpanel/caller/spam.py
cpanel/caller/ssh.py
cpanel/caller/stats.py
cpanel/caller/subaccounts.py
cpanel/caller/themes.py
cpanel/caller/usage.py
cpanel/caller/webmail.py
cpanel_cli-0.29.dist-info/METADATA
cpanel_cli-0.29.dist-info/WHEEL
cpanel_cli-0.29.dist-info/entry_points.txt
cpanel_cli-0.29.dist-info/licenses/LICENSE
cpanel_cli-0.29.dist-info/RECORD
