Metadata-Version: 2.3
Name: cpanel-cli
Version: 0.29
Summary: A command line interface for the cPanel Unrestricted API.
Project-URL: Homepage, https://github.com/layfellow/cpanel-cli
Project-URL: Documentation, https://cpanel-cli.readthedocs.io/
Project-URL: Repository, https://github.com/layfellow/cpanel-cli
Project-URL: Bug Tracker, https://github.com/layfellow/cpanel-cli/issues
Author-email: Marco Bravo Mejías <marco@layfellow.net>
License: GNU General Public License v3 (GPLv3)
Keywords: cli,command-line,cpanel,hosting
Classifier: License :: OSI Approved :: GNU General Public License v3 (GPLv3)
Classifier: Operating System :: OS Independent
Classifier: Programming Language :: Python :: 3
Requires-Python: >=3.11
Requires-Dist: cpanel-api>=0.3.0
Requires-Dist: parsedatetime>=2.6
Provides-Extra: dev
Requires-Dist: build>=1.2; extra == 'dev'
Requires-Dist: cpanel-api>=0.3.0; extra == 'dev'
Requires-Dist: parsedatetime>=2.6; extra == 'dev'
Requires-Dist: sphinx-book-theme>=1.1.3; extra == 'dev'
Requires-Dist: sphinx-intl>=2.2.0; extra == 'dev'
Requires-Dist: sphinx>=5.0; extra == 'dev'
Requires-Dist: tox>=4.22; extra == 'dev'
Requires-Dist: twine>=5.1.1; extra == 'dev'
